[
  {
    "id": 101,
    "active": true,
    "age": 21,
    "firstName": "Martin",
    "lastName": "Ridesdale"
  },
  {
    "id": 102,
    "active": true,
    "age": 42,
    "firstName": "Curcio",
    "lastName": "Pitherick"
  },
  {
    "id": 103,
    "active": true,
    "age": 34,
    "firstName": "Sherwynd",
    "lastName": "Slimings"
  },
  {
    "id": 104,
    "active": false,
    "age": 72,
    "firstName": "Seumas",
    "lastName": "Suarez"
  },
  {
    "id": 105,
    "active": true,
    "age": 51,
    "firstName": "Sisile",
    "lastName": "Louis"
  },
  {
    "id": 106,
    "active": true,
    "age": 50,
    "firstName": "Kilian",
    "lastName": "Pittam"
  },
  {
    "id": 107,
    "active": true,
    "age": 53,
    "firstName": "Vivyanne",
    "lastName": "Ashmore"
  },
  {
    "id": 108,
    "active": true,
    "age": 49,
    "firstName": "Aksel",
    "lastName": "Hortop"
  },
  {
    "id": 109,
    "active": true,
    "age": 18,
    "firstName": "Birk",
    "lastName": "Alves"
  },
  {
    "id": 110,
    "active": true,
    "age": 38,
    "firstName": "Lauren",
    "lastName": "Eliesco"
  },
  {
    "id": 111,
    "active": false,
    "age": 65,
    "firstName": "Eugene",
    "lastName": "Moyles"
  },
  {
    "id": 112,
    "active": false,
    "age": 75,
    "firstName": "Karoline",
    "lastName": "Hourston"
  },
  {
    "id": 113,
    "active": true,
    "age": 28,
    "firstName": "Stormi",
    "lastName": "Crowley"
  },
  {
    "id": 114,
    "active": true,
    "age": 39,
    "firstName": "Daria",
    "lastName": "Zielinski"
  },
  {
    "id": 115,
    "active": true,
    "age": 18,
    "firstName": "Selby",
    "lastName": "Caveney"
  },
  {
    "id": 116,
    "active": false,
    "age": 61,
    "firstName": "Cooper",
    "lastName": "Fanthome"
  },
  {
    "id": 117,
    "active": true,
    "age": 32,
    "firstName": "Valentijn",
    "lastName": "O'Hollegan"
  },
  {
    "id": 118,
    "active": true,
    "age": 59,
    "firstName": "Bobbe",
    "lastName": "O'Moylane"
  },
  {
    "id": 119,
    "active": true,
    "age": 22,
    "firstName": "Erinna",
    "lastName": "Raeside"
  },
  {
    "id": 120,
    "active": true,
    "age": 42,
    "firstName": "Aili",
    "lastName": "Saiger"
  },
  {
    "id": 121,
    "active": true,
    "age": 29,
    "firstName": "Chrotoem",
    "lastName": "de Chastelain"
  },
  {
    "id": 122,
    "active": false,
    "age": 74,
    "firstName": "Dulcine",
    "lastName": "Honatsch"
  },
  {
    "id": 123,
    "active": true,
    "age": 19,
    "firstName": "Fons",
    "lastName": "O'Malley"
  },
  {
    "id": 124,
    "active": true,
    "age": 50,
    "firstName": "Adella",
    "lastName": "MacCall"
  },
  {
    "id": 125,
    "active": true,
    "age": 48,
    "firstName": "Dimitri",
    "lastName": "Rasor"
  },
  {
    "id": 126,
    "active": true,
    "age": 29,
    "firstName": "Leroi",
    "lastName": "Paulucci"
  },
  {
    "id": 127,
    "active": true,
    "age": 32,
    "firstName": "Audrie",
    "lastName": "Barnhill"
  },
  {
    "id": 128,
    "active": false,
    "age": 66,
    "firstName": "Leanna",
    "lastName": "Burwood"
  },
  {
    "id": 129,
    "active": false,
    "age": 65,
    "firstName": "Oswald",
    "lastName": "Domenget"
  },
  {
    "id": 130,
    "active": true,
    "age": 31,
    "firstName": "Frances",
    "lastName": "Goady"
  },
  {
    "id": 131,
    "active": false,
    "age": 76,
    "firstName": "Chantal",
    "lastName": "McCane"
  },
  {
    "id": 132,
    "active": true,
    "age": 32,
    "firstName": "Hagen",
    "lastName": "Blackston"
  },
  {
    "id": 133,
    "active": false,
    "age": 76,
    "firstName": "Lewie",
    "lastName": "Harness"
  },
  {
    "id": 134,
    "active": false,
    "age": 69,
    "firstName": "Morris",
    "lastName": "Ducarne"
  },
  {
    "id": 135,
    "active": true,
    "age": 32,
    "firstName": "Blinni",
    "lastName": "Boughey"
  },
  {
    "id": 136,
    "active": true,
    "age": 32,
    "firstName": "Aarika",
    "lastName": "Buddle"
  },
  {
    "id": 137,
    "active": false,
    "age": 77,
    "firstName": "Arluene",
    "lastName": "Scad"
  },
  {
    "id": 138,
    "active": false,
    "age": 62,
    "firstName": "Carolann",
    "lastName": "Bramwell"
  },
  {
    "id": 139,
    "active": false,
    "age": 75,
    "firstName": "Marcela",
    "lastName": "Spencers"
  },
  {
    "id": 140,
    "active": true,
    "age": 37,
    "firstName": "Gareth",
    "lastName": "Shovel"
  },
  {
    "id": 141,
    "active": true,
    "age": 32,
    "firstName": "Horacio",
    "lastName": "Bremmell"
  },
  {
    "id": 142,
    "active": false,
    "age": 74,
    "firstName": "Georgina",
    "lastName": "Westcot"
  },
  {
    "id": 143,
    "active": true,
    "age": 28,
    "firstName": "Nari",
    "lastName": "Chevers"
  },
  {
    "id": 144,
    "active": false,
    "age": 71,
    "firstName": "Ralina",
    "lastName": "Hankin"
  },
  {
    "id": 145,
    "active": true,
    "age": 33,
    "firstName": "Cybill",
    "lastName": "Lantaff"
  },
  {
    "id": 146,
    "active": true,
    "age": 18,
    "firstName": "Mac",
    "lastName": "Warrillow"
  },
  {
    "id": 147,
    "active": true,
    "age": 24,
    "firstName": "Mitch",
    "lastName": "MacEllen"
  },
  {
    "id": 148,
    "active": true,
    "age": 26,
    "firstName": "Meir",
    "lastName": "Avramov"
  },
  {
    "id": 149,
    "active": true,
    "age": 54,
    "firstName": "Merrile",
    "lastName": "Bomb"
  },
  {
    "id": 150,
    "active": true,
    "age": 32,
    "firstName": "Bathsheba",
    "lastName": "Waker"
  },
  {
    "id": 151,
    "active": true,
    "age": 58,
    "firstName": "Sunny",
    "lastName": "Corhard"
  },
  {
    "id": 152,
    "active": true,
    "age": 57,
    "firstName": "Shayna",
    "lastName": "Rappa"
  },
  {
    "id": 153,
    "active": true,
    "age": 59,
    "firstName": "Zita",
    "lastName": "Duiguid"
  },
  {
    "id": 154,
    "active": true,
    "age": 49,
    "firstName": "Franky",
    "lastName": "Boobier"
  },
  {
    "id": 155,
    "active": false,
    "age": 66,
    "firstName": "Kristos",
    "lastName": "Gilhooley"
  },
  {
    "id": 156,
    "active": true,
    "age": 54,
    "firstName": "Aubert",
    "lastName": "Thornally"
  },
  {
    "id": 157,
    "active": true,
    "age": 32,
    "firstName": "Lucretia",
    "lastName": "Ianno"
  },
  {
    "id": 158,
    "active": true,
    "age": 42,
    "firstName": "Urban",
    "lastName": "Whitlow"
  },
  {
    "id": 159,
    "active": false,
    "age": 66,
    "firstName": "Harold",
    "lastName": "Rhubottom"
  },
  {
    "id": 160,
    "active": false,
    "age": 69,
    "firstName": "Catharina",
    "lastName": "Banville"
  },
  {
    "id": 161,
    "active": true,
    "age": 54,
    "firstName": "Clerc",
    "lastName": "Walework"
  },
  {
    "id": 162,
    "active": false,
    "age": 64,
    "firstName": "Randi",
    "lastName": "Tonbye"
  },
  {
    "id": 163,
    "active": false,
    "age": 80,
    "firstName": "Louie",
    "lastName": "Crosscombe"
  },
  {
    "id": 164,
    "active": false,
    "age": 78,
    "firstName": "Arch",
    "lastName": "Shortell"
  },
  {
    "id": 165,
    "active": true,
    "age": 36,
    "firstName": "Leigh",
    "lastName": "Privost"
  },
  {
    "id": 166,
    "active": false,
    "age": 76,
    "firstName": "Nicola",
    "lastName": "Oakenfall"
  },
  {
    "id": 167,
    "active": true,
    "age": 34,
    "firstName": "Ira",
    "lastName": "Gresham"
  },
  {
    "id": 168,
    "active": false,
    "age": 66,
    "firstName": "Shandie",
    "lastName": "Slee"
  },
  {
    "id": 169,
    "active": true,
    "age": 55,
    "firstName": "Archambault",
    "lastName": "Oscroft"
  },
  {
    "id": 170,
    "active": true,
    "age": 50,
    "firstName": "Myrwyn",
    "lastName": "Kiledal"
  },
  {
    "id": 171,
    "active": true,
    "age": 55,
    "firstName": "Robinett",
    "lastName": "Hradsky"
  },
  {
    "id": 172,
    "active": true,
    "age": 26,
    "firstName": "Daniel",
    "lastName": "Duthy"
  },
  {
    "id": 173,
    "active": true,
    "age": 19,
    "firstName": "Daveen",
    "lastName": "D'Errico"
  },
  {
    "id": 174,
    "active": true,
    "age": 27,
    "firstName": "Jaquelyn",
    "lastName": "Fer"
  },
  {
    "id": 175,
    "active": false,
    "age": 74,
    "firstName": "Anallise",
    "lastName": "Edgerly"
  },
  {
    "id": 176,
    "active": false,
    "age": 72,
    "firstName": "Hilary",
    "lastName": "Marcroft"
  },
  {
    "id": 177,
    "active": true,
    "age": 25,
    "firstName": "Kippar",
    "lastName": "Butner"
  },
  {
    "id": 178,
    "active": true,
    "age": 35,
    "firstName": "Brant",
    "lastName": "Benezeit"
  },
  {
    "id": 179,
    "active": true,
    "age": 31,
    "firstName": "Rachele",
    "lastName": "Bissett"
  },
  {
    "id": 180,
    "active": true,
    "age": 35,
    "firstName": "Moishe",
    "lastName": "Pridham"
  },
  {
    "id": 181,
    "active": true,
    "age": 48,
    "firstName": "Bran",
    "lastName": "Robbey"
  },
  {
    "id": 182,
    "active": true,
    "age": 23,
    "firstName": "Shawn",
    "lastName": "Ishaki"
  },
  {
    "id": 183,
    "active": true,
    "age": 20,
    "firstName": "Killian",
    "lastName": "Braunfeld"
  },
  {
    "id": 184,
    "active": false,
    "age": 64,
    "firstName": "Ranee",
    "lastName": "Aartsen"
  },
  {
    "id": 185,
    "active": true,
    "age": 34,
    "firstName": "Trudi",
    "lastName": "Asple"
  },
  {
    "id": 186,
    "active": true,
    "age": 29,
    "firstName": "Roderich",
    "lastName": "Hazeup"
  },
  {
    "id": 187,
    "active": true,
    "age": 29,
    "firstName": "Monroe",
    "lastName": "Veevers"
  },
  {
    "id": 188,
    "active": true,
    "age": 26,
    "firstName": "Enriqueta",
    "lastName": "Costi"
  },
  {
    "id": 189,
    "active": true,
    "age": 48,
    "firstName": "Patrice",
    "lastName": "Stadden"
  },
  {
    "id": 190,
    "active": true,
    "age": 44,
    "firstName": "Sorcha",
    "lastName": "Alcock"
  },
  {
    "id": 191,
    "active": true,
    "age": 52,
    "firstName": "Templeton",
    "lastName": "Foulis"
  },
  {
    "id": 192,
    "active": false,
    "age": 68,
    "firstName": "Frans",
    "lastName": "Sellner"
  },
  {
    "id": 193,
    "active": false,
    "age": 65,
    "firstName": "Marsha",
    "lastName": "Tulloch"
  },
  {
    "id": 194,
    "active": false,
    "age": 74,
    "firstName": "Annabela",
    "lastName": "Cadore"
  },
  {
    "id": 195,
    "active": true,
    "age": 23,
    "firstName": "Tyrus",
    "lastName": "Clampin"
  },
  {
    "id": 196,
    "active": true,
    "age": 27,
    "firstName": "Rheta",
    "lastName": "Crownshaw"
  },
  {
    "id": 197,
    "active": true,
    "age": 49,
    "firstName": "Georgy",
    "lastName": "Nutkin"
  },
  {
    "id": 198,
    "active": true,
    "age": 45,
    "firstName": "Jakob",
    "lastName": "Attwoull"
  },
  {
    "id": 199,
    "active": false,
    "age": 65,
    "firstName": "Lilla",
    "lastName": "Sackes"
  },
  {
    "id": 200,
    "active": true,
    "age": 43,
    "firstName": "Charmine",
    "lastName": "Tremmil"
  }
]